[
    {
        "name": "APPADMIN",
        "privilege": [
            "View Organization",
            "Edit Organization",
            "Delete Organization",
            "App Dashboard",
            "Dashboard",
            "View User",
            "Edit User",
            "Delete User",
            "Reset Password",
            "View User Log",
            "Add Role",
            "Edit Role",
            "Delete Role",
            "View Role",
            "Add Department",
            "Edit Department",
            "Delete Department",
            "View Department",
            "Add File",
            "Edit File",
            "Delete File",
            "View File Log",
            "Add Sub Department",
            "Edit Sub Department",
            "Delete Sub Department",
            "View Sub Department",
            "View File Log,",
            "Add Designation",
            "Edit Designation",
            "Delete Designation",
            "View Designation",
            "Add Section",
            "Edit Section",
            "Delete Section",
            "View Section",
            "Add Reference",
            "Edit Reference",
            "Delete Reference",
            "View Reference",
            "View Activity Log",
            "Change File Status",
            "Add Note",
            "View Note",
            "Edit Note",
            "Delete Note",
            "Add Document",
            "Edit Document",
            "Delete Document",
            "Add Link",
            "Remove Link",
            "Add Reference",
            "Edit Reference",
            "View Reference",
            "View All File",
            "Edit Share File",
            "Delete Share File",
            "Multiple Share File",
            "Download PDF"
        ]
    },
    {
        "name": "APPUSER",
        "privilege": [
            "View Organization",
            "Edit Organization",
            "Delete Organization",
            "App Dashboard",
            "Dashboard",
            "View User",
            "Edit User",
            "Delete User",
            "Reset Password",
            "View User Log",
            "Add Role",
            "Edit Role",
            "Delete Role",
            "View Role",
            "Add Department",
            "Edit Department",
            "Delete Department",
            "View Department",
            "Add File",
            "Edit File",
            "Delete File",
            "View File Log",
            "Add Sub Department",
            "Edit Sub Department",
            "Delete Sub Department",
            "View Sub Department",
            "View File Log,",
            "Add Designation",
            "Edit Designation",
            "Delete Designation",
            "View Designation",
            "Add Section",
            "Edit Section",
            "Delete Section",
            "View Section",
            "Add Reference",
            "Edit Reference",
            "Delete Reference",
            "View Reference",
            "View Activity Log",
            "Change File Status",
            "Add Note",
            "View Note",
            "Edit Note",
            "Delete Note",
            "Add Document",
            "Edit Document",
            "Delete Document",
            "Add Link",
            "Remove Link",
            "Add Reference",
            "Edit Reference",
            "View Reference",
            "View All File",
            "Edit Share File",
            "Delete Share File",
            "Multiple Share File",
            "Download PDF"
        ]
    },
    {
        "name": "ADMIN",
        "privilege": [
            "View Organization",
            "Edit Organization",
            "Delete Organization",
            "Dashboard",
            "View User",
            "Edit User",
            "Delete User",
            "Reset Password",
            "View User Log",
            "Add Role",
            "Edit Role",
            "Delete Role",
            "View Role",
            "Add Department",
            "Edit Department",
            "Delete Department",
            "View Department",
            "Add File",
            "Edit File",
            "Delete File",
            "View File Log",
            "Add Sub Department",
            "Edit Sub Department",
            "Delete Sub Department",
            "View Sub Department",
            "View File Log,",
            "Add Designation",
            "Edit Designation",
            "Delete Designation",
            "View Designation",
            "Add Section",
            "Edit Section",
            "Delete Section",
            "View Section",
            "Add Reference",
            "Edit Reference",
            "Delete Reference",
            "View Reference",
            "View Activity Log",
            "Change File Status",
            "Add Note",
            "View Note",
            "Edit Note",
            "Delete Note",
            "Add Document",
            "Edit Document",
            "Delete Document",
            "Add Link",
            "Remove Link",
            "Add Reference",
            "Edit Reference",
            "View Reference",
            "View All File",
            "Edit Share File",
            "Delete Share File",
            "Multiple Share File",
            "Download PDF"
        ]
    },
    {
        "name": "DEPARTMENTADMIN",
        "privilege": [
            "View User",
            "Add File",
            "Edit File",
            "Change File Status",
            "Add Note",
            "View Note",
            "Add Document",
            "Edit Document",
            "Add Link",
            "Remove Link",
            "Add Reference",
            "View Reference",
            "View Department File",
            "Edit Share File",
            "Delete Share File",
            "Multiple Share File",
            "Download PDF"
        ]
    },
    {
        "name": "DEPARTMENTUSER",
        "privilege": [
            "View User",
            "Add File",
            "View Note",
            "Add Document",
            "Add Link",
            "Add Reference",
            "View Reference",
            "View File"
        ]
    },
    {
        "name": "SUBDEPARTMENTADMIN",
        "privilege": [
            "View User",
            "Add File",
            "Edit File",
            "Change File Status",
            "Add Note",
            "View Note",
            "Add Document",
            "Edit Document",
            "Add Link",
            "Remove Link",
            "Add Reference",
            "Edit Reference",
            "View Reference",
            "View Sub Department File",
            "Edit Share File",
            "Delete Share File"
        ]
    },
    {
        "name": "SUBDEPARTMENTUSER",
        "privilege": [
            "View User",
            "Add File",
            "View Note",
            "Add Document",
            "Add Link",
            "Add Reference",
            "View Reference",
            "View File"
        ]
    },
    {
        "name": "SECTIONADMIN",
        "privilege": [
            "View User",
            "Add File",
            "Edit File",
            "Change File Status",
            "Add Note",
            "View Note",
            "Add Document",
            "Edit Document",
            "Add Link",
            "Remove Link",
            "Add Reference",
            "Edit Reference",
            "View Reference",
            "View Section File",
            "Edit Share File",
            "Delete Share File"
        ]
    },
    {
        "name": "SECTIONUSER",
        "privilege": [
            "View User",
            "Add File",
            "View Note",
            "Add Document",
            "Add Link",
            "Add Reference",
            "View Reference",
            "View File"
        ]
    }
]